signalwire_swml/__init__.py
signalwire_swml/ordered.py
signalwire_swml/swml.py
signalwire_swml-2.7.dist-info/licenses/LICENSE
signalwire_swml-2.7.dist-info/METADATA
signalwire_swml-2.7.dist-info/WHEEL
signalwire_swml-2.7.dist-info/top_level.txt
signalwire_swml-2.7.dist-info/RECORD
