Metadata-Version: 2.4
Name: signalwire-swml
Version: 2.7
Summary: A Python package for generating SignalWire Markup Language (SWML)
Author-email: SignalWire <support@signalwire.com>
License-Expression: MIT
Project-URL: Homepage, https://github.com/briankwest/signalwire-swml
Project-URL: Issues, https://github.com/briankwest/signalwire-swml/issues
Classifier: Programming Language :: Python :: 3
Classifier: Operating System :: OS Independent
Requires-Python: >=3.6
License-File: LICENSE
Requires-Dist: docopt
Requires-Dist: pyyaml
Dynamic: license-file
